aforcioligetscode/__init__.py
aforcioligetscode/script.py
aforcioligetscode-0.1.0.dist-info/entry_points.txt
aforcioligetscode-0.1.0.dist-info/WHEEL
aforcioligetscode-0.1.0.dist-info/METADATA
aforcioligetscode-0.1.0.dist-info/RECORD
